libname/__init__.py
libname/hello.py
hellopkgismail-0.0.2.dist-info/METADATA
hellopkgismail-0.0.2.dist-info/WHEEL
hellopkgismail-0.0.2.dist-info/top_level.txt
hellopkgismail-0.0.2.dist-info/RECORD
