Metadata-Version: 2.1
Name: hellopkgismail
Version: 0.0.2
Summary: A basic hello package
Home-page: UNKNOWN
Author: Ismail Chbiki
Author-email: ismailchbiki.nl@gmail.com
License: UNKNOWN
Keywords: python,hello,hello package
Platform: UNKNOWN
Classifier: Development Status :: 1 - Planning
Classifier: Intended Audience :: Developers
Classifier: Programming Language :: Python :: 3
Classifier: Operating System :: Unix
Classifier: Operating System :: MacOS :: MacOS X
Classifier: Operating System :: Microsoft :: Windows
